{"Hertfordshire": ["A", "C", "E", "S", "H", "U", "W", "L", "R"], "Dorset": ["D", "C", "T", "E", "P", "S", "B", "G"], "Greater Manchester": ["O", "D", "C", "M", "P", "S", "F", "W", "L", "B", "I"], "Greater London": ["D", "C", "K", "T", "E", "N", "S", "H", "U", "W", "B", "I", "R"], "West Midlands": ["D", "C", "W", "L", "B"], "West Yorkshire": ["O", "D", "S", "H", "W", "L", "B", "I"], "Lancashire": ["O", "E", "F", "P", "W", "L", "B"], "South Gloucestershire": ["R", "S", "B", "G"], "Staffordshire": ["D", "C", "M", "T", "S", "W", "B"], "Bournemouth, Christchurch And Poole": ["P", "B", "D"], "Blackburn With Darwen": ["F", "B", "O", "P"], "West Sussex": ["C", "P", "S", "R", "B", "G"], "City Of Bristol": ["W", "S", "B", "G"], "North Somerset": ["T", "B", "P"], "East Sussex": ["T", "P", "W", "B", "R"], "Wiltshire": ["R", "C", "E", "P", "S", "W", "B", "I", "G"], "Bath And North East Somerset": ["T", "B", "D", "C"], "North Yorkshire": ["D", "C", "T", "Y", "H", "W", "L", "B"], "Brighton And Hove": ["R", "T", "B", "P"], "Somerset": ["D", "T", "E", "P", "B"], "Hampshire": ["R", "P", "S", "W", "B", "G"], "Warwickshire": ["R", "O", "C", "N", "W", "L", "B", "G"], "Worcestershire": ["R", "D", "C", "S", "H", "W", "B", "G"], "Kent": ["D", "C", "M", "T", "S", "B", "R"], "Cardiff": ["N", "S", "L", "C"], "Cambridgeshire": ["C", "M", "P", "S", "B"], "The Vale Of Glamorgan": ["N", "S", "C"], "Essex": ["C", "M", "E", "P", "S", "L", "B", "I", "R"], "Cheshire East": ["W", "P", "S", "C"], "Merseyside": ["C", "T", "P", "S", "U", "W", "L"], "Surrey": ["C", "T", "K", "N", "S", "R", "G"], "Cumbria": ["O", "D", "C", "T", "P", "L"], "Cheshire West And Chester": ["W", "S", "L", "C"], "Bridgend": ["N", "S", "C"], "Flintshire": ["N", "S", "L", "C"], "Suffolk": ["N", "D", "I", "C"], "Merthyr Tydfil": ["N", "S", "L", "C"], "Rhondda Cynon Taff": ["D", "C", "N", "S", "W", "L"], "Northamptonshire": ["O", "D", "C", "M", "N", "P", "W", "L"], "Leicestershire": ["D", "C", "N", "P", "S", "L"], "Caerphilly": ["N", "S", "L", "C"], "Denbighshire": ["D", "C", "N", "S", "L"], "Newport": ["N", "S", "L", "C"], "Shropshire": ["D", "C", "T", "S", "W", "L", "B"], "Northumberland": ["N", "T", "D", "C"], "West Northamptonshire": ["O", "C", "M", "N", "L"], "Powys": ["C", "N", "S", "H", "L"], "North East Lincolnshire": ["L", "D", "H"], "Lincolnshire": ["D", "N", "P", "L", "I"], "Derbyshire": ["O", "D", "N", "S", "W", "L"], "South Yorkshire": ["O", "D", "N", "S", "H", "W", "L", "I"], "North Lincolnshire": ["L", "D", "H"], "County Durham": ["D", "T", "N", "P", "S"], "City Of Derby": ["N", "S", "D"], "East Riding Of Yorkshire": ["D", "T", "N", "Y", "H"], "Tyne And Wear": ["N", "S", "D"], "Nottinghamshire": ["D", "N", "S", "H", "L"], "Darlington": ["T", "D"], "Devon": ["D", "T", "E", "P", "S", "B"], "Warrington": ["W", "S", "D", "C"], "Cornwall": ["T", "E", "P", "L", "B"], "Central Bedfordshire": ["A", "M", "E", "P", "S", "H", "L"], "Blackpool": ["F", "L", "B", "P"], "Gloucestershire": ["R", "O", "N", "S", "H", "W", "B", "G"], "Oxfordshire": ["O", "C", "M", "N", "S", "H", "R", "G"], "Bracknell Forest": ["R", "S", "B", "G"], "Herefordshire": ["N", "S", "H", "W", "L", "G"], "Buckinghamshire": ["O", "M", "N", "S", "H", "U", "W", "L", "R"], "City Of Kingston Upon Hull": ["P", "D", "H"], "Milton Keynes": ["M", "N", "S", "H", "L"], "Norfolk": ["O", "C", "N", "P", "I"], "Conwy": ["N", "S", "L", "C"], "Luton": ["M", "S", "L", "C"], "Gwynedd": ["C", "N", "S", "W", "L"], "Leicester": ["D", "C", "M", "N", "P", "S", "L"], "Isle Of Anglesey": ["N", "L", "C"], "Wrexham": ["C", "N", "S", "H", "L"], "Rutland": ["N", "P", "L", "D"], "Halton": ["W", "P", "L", "C"], "North Northamptonshire": ["N", "P", "L"], "Bedford": ["M", "N", "P", "S", "L"], "Medway": ["M", "T", "D", "C"], "Blaenau Gwent": ["N", "S", "L", "C"], "City Of Nottingham": ["N", "S", "D", "L"], "Torfaen": ["N", "S", "L", "C"], "Monmouthshire": ["N", "S", "C", "G"], "Isle Of Wight": ["T", "N", "P", "B", "R"], "City Of Peterborough": ["P", "C"], "Portsmouth": ["T", "P", "S", "R", "B", "G"], "City Of Plymouth": ["E", "T", "P"], "Reading": ["R", "S", "B", "G"], "Wokingham": ["O", "C", "S", "R", "B", "G"], "West Berkshire": ["O", "G", "S", "B", "R"], "Thurrock": ["R", "S", "I", "C"], "Windsor And Maidenhead": ["O", "T", "S", "R", "B", "G"], "Swindon": ["S", "B"], "Southend-On-Sea": ["R", "S", "I", "C"], "Carmarthenshire": ["N", "S", "C"], "Swansea": ["N", "S", "L", "C"], "Stoke-On-Trent": ["D", "C", "S", "W", "B"], "Southampton": ["G", "P", "S", "B", "R"], "Pembrokeshire": ["N", "S", "C"], "Neath Port Talbot": ["N", "S", "L", "C"], "Slough": ["O", "T", "S", "B", "R"], "Ceredigion": ["S", "C"], "Wrekin": ["W", "T", "S"], "Redcar And Cleveland": ["T", "S"], "Stockton-On-Tees": ["T", "S", "D"], "Torbay": ["E", "T", "Y", "P"], "Hartlepool": ["T", "C"], "Middlesbrough": ["T"], "Isles Of Scilly": ["T"], "York": ["D", "T", "Y", "H", "L", "B"], "Poole": ["D", "P", "S", "B", "G"], "Bournemouth": ["D", "G", "S", "B", "R"], "Cheshire": ["C", "M", "S", "W", "L"], "Bedfordshire": ["A", "C", "M", "N", "P", "S", "H", "L"], "Cleveland": ["T"], "Avon": ["S", "B", "G"], "Durham": ["N", "T", "S", "D"], "Berkshire": ["O", "S", "R"], "Hereford And Worcester": ["D", "N", "S", "H", "W", "L", "B", "G"], "Thamesdown": ["S", "B"], "South Glamorgan": ["C"], "Mid Glamorgan": ["N", "S", "C"], "Clwyd": ["S", "L", "C"], "Humberside": ["Y", "L", "D", "H"], "Gwent": ["N", "L", "C"], "West Glamorgan": ["S", "C"], "Dyfed": ["S"]}